.hgignore
.hgtags
CHANGES.txt
LICENSE.txt
README.txt
TODO.txt
bootstrap.py
buildout.cfg
setup.py
src/gocept/__init__.py
src/gocept.exttest.egg-info/PKG-INFO
src/gocept.exttest.egg-info/SOURCES.txt
src/gocept.exttest.egg-info/dependency_links.txt
src/gocept.exttest.egg-info/namespace_packages.txt
src/gocept.exttest.egg-info/not-zip-safe
src/gocept.exttest.egg-info/requires.txt
src/gocept.exttest.egg-info/top_level.txt
src/gocept/exttest/__init__.py
src/gocept/exttest/case.py
src/gocept/exttest/tests/__init__.py
src/gocept/exttest/tests/test_case.py