Metadata-Version: 1.0
Name: gocept.exttest
Version: 0.1.2
Summary: Helper to run external commands as tests with zc.testrunner.
Home-page: http://code.gocept.com/hg/public/gocept.exttest
Author: gocept
Author-email: mail@gocept.com
License: ZPL
Platform: UNKNOWN
